clustlib/__init__.py
clustlib/_base/__init__.py
clustlib/_base/elkan.py
clustlib/_base/kmean.py
clustlib/_base/lloyd.py
clustlib/_typing.py
clustlib/fuzzy/__init__.py
clustlib/fuzzy/lcvqe.py
clustlib/gac/__init__.py
clustlib/gac/_base.py
clustlib/gac/brkga.py
clustlib/gac/shade.py
clustlib/kmean/__init__.py
clustlib/kmean/copkmeans.py
clustlib/kmean/rdpmean.py
clustlib/metrics.py
clustlib/model.py
clustlib/nonparam/__init__.py
clustlib/nonparam/tvclust.py
clustlib/sin/__init__.py
clustlib/sin/dils.py
clustlib/utils/__init__.py
clustlib/utils/distance.py
clustlib/utils/initilize.py
clustlib/utils/simpleconstraints.py
clustlib-0.1.0.dist-info/LICENSE
clustlib-0.1.0.dist-info/METADATA
clustlib-0.1.0.dist-info/WHEEL
clustlib-0.1.0.dist-info/RECORD
