Metadata-Version: 2.3
Name: clustlib
Version: 0.1.0
Summary: Constrained clustering library for Python
Author: Ismael Marin
Author-email: ismitae.imm@gmail.com
Maintainer: Ismael Marin
Maintainer-email: ismitae.imm@gmail.com
Requires-Python: >= 3.12, < 3.13.3
Classifier: Programming Language :: Python :: 3
Classifier: Programming Language :: Python :: 3.12
Classifier: Programming Language :: Python :: 3.13
Requires-Dist: networkx (>=3.4.2)
Requires-Dist: numpy (>=1.26.2)
Requires-Dist: scikit-learn (>=1.3.1)
Requires-Dist: scipy (>=1.16.1)
